tellor/__init__.py
tellor/abi/tellor.json
tellor/auto.py
tellor/constants.py
tellor/contract.py
tellor/dispute.py
tellor/func_decoders.py
tellor/log_decoders.py
tellor/types.py
tellor-0.3.8.dist-info/WHEEL
tellor-0.3.8.dist-info/METADATA
tellor-0.3.8.dist-info/RECORD
